shankarlohar/__init__.py
shankarlohar/main.py
shankarlohar-0.1.3.dist-info/LICENSE
shankarlohar-0.1.3.dist-info/METADATA
shankarlohar-0.1.3.dist-info/WHEEL
shankarlohar-0.1.3.dist-info/RECORD
