Metadata-Version: 2.1
Name: shankarlohar
Version: 0.1.3
Summary: 
Author: shankarlohar
Author-email: inbox.shankarlohar@gmail.com
Requires-Python: >=3.10.0,<4.0.0
Classifier: Programming Language :: Python :: 3
Classifier: Programming Language :: Python :: 3.10
Classifier: Programming Language :: Python :: 3.11
Classifier: Programming Language :: Python :: 3.12
